Workbook

Sheet underwriting
B1: STR INVESTMENT UNDERWRITING
B2: Address: | D2: {{address}}
C4: Assumption | D4: Low | E4: Mid | F4: High | H4: HOLDING COSTS | I4: Monthly | J4: Yearly
B5: PROPERTY INFO | H5: Internet | I5: 100 | J5: =I5*12 -> 1200
B6: Bedrooms | D6: 6 | H6: Water | I6: 0 | J6: =I6*12 -> 0
B7: Bathrooms | D7: 4 | H7: Electricity | I7: 100 | J7: =I7*12 -> 1200
B8: Square Footage | D8: 3000 | H8: Natural Gas | I8: 0 | J8: =I8*12 -> 0
B9: Market | D9: {{market}} | H9: Pest Control | I9: 13 | J9: =I9*12 -> 156
H10: Pool Maintenance | I10: 200 | J10: =I10*12 -> 2400
B11: PURCHASE DETAILS & FINANCING | H11: Outdoor / Landscaping | I11: 150 | J11: =I11*12 -> 1800
B12: Purchase Price | D12: 850000 | H12: Garbage | I12: 50 | J12: =I12*12 -> 600
B13: Down Payment | C13: 0.1 | D13: =D12*C13 -> 85000 | H13: Supplies | I13: 0 | J13: =I13*12 -> 0
B14: Loan Amount | D14: =D12-D13 -> 765000 | H14: Cleaning | I14: 0 | J14: =I14*12 -> 0
B15: Interest Rate | C15: 0.07 | H15: Property Taxes | I15: 200 | J15: =I15*12 -> 2400
B16: Loan Term (Yrs) | C16: 30 | H16: Home Insurance | I16: 250 | J16: =I16*12 -> 3000
B17: Loan Type | D17: conventional | H17: Mortgage | I17: =D20 -> 5089.5641 | J17: =I17*12 -> 61074.769
B18: Closing Costs | C18: 0.03 | D18: =D12*C18 -> 25500 | H18: Total Holding Costs | I18: =SUM(I5:I17) -> 6152.5641 | J18: =I18*12 -> 73830.769
B19: Mortgage Insurance (Annual) | C19: 0.005 | D19: =D14*C19 -> 3825
B20: Monthly Payment | D20: =IF(C15=0,D14/(C16*12),(D14*(C15/12)*(1+C15/12)^(C16*12))/((1+C15/12)^(C16*12)-1)) -> 5089.5641
B21: Annual Debt Service | D21: =D20*12 -> 61074.769
B22: Year 1 Principal Paydown | D22: =D21-D14*C15 -> 7524.7691
B24: SET UP COSTS
B25: Renovation / Amenities / Furniture | D25: 0
B26: Other | D26: 0
B27: Total Set Up | D27: =D25+D26 -> 0
B28: TOTAL CASH TO CLOSE | D28: =D13+D18+D27 -> 110500
B30: REVENUE ESTIMATE
B31: Average Daily Rate (ADR) | D31: 275 | E31: 325 | F31: 375
B32: Occupancy Rate | D32: 0.58 | E32: 0.65 | F32: 0.72
B33: Gross Annual Revenue | D33: =D31*D32*365 -> 58217.5 | E33: =E31*E32*365 -> 77106.25 | F33: =F31*F32*365 -> 98550
B34: Avg Stay (Nights) | C34: 3.5
B35: Est. Annual Turns | D35: =ROUND(365*D32/C34,0) -> 60 | E35: =ROUND(365*E32/C34,0) -> 68 | F35: =ROUND(365*F32/C34,0) -> 75
B36: Data Source / Confidence | D36: {{data_source}}
B38: OPERATING EXPENSES | C38: Assumption
B39: Platform Fees (% of revenue) | C39: 0.03 | D39: =D33*C39 -> 1746.525 | E39: =E33*C39 -> 2313.1875 | F39: =F33*C39 -> 2956.5
B40: Property Management (% of revenue) | C40: 0.2 | D40: =D33*C40 -> 11643.5 | E40: =E33*C40 -> 15421.25 | F40: =F33*C40 -> 19710
B41: Cleaning (per turn × turns, by beds) | C41: =IF(D6>=8,550,IF(D6=7,450,IF(D6=6,400,350))) -> 400 | D41: =C41*D35 -> 24000 | E41: =C41*E35 -> 27200 | F41: =C41*F35 -> 30000
B42: Supplies — Annual (by beds) | C42: =IF(D6>=8,800,IF(D6=7,700,IF(D6=6,500,400))) -> 500 | D42: =C42 -> 500 | E42: =C42 -> 500 | F42: =C42 -> 500
B43: Utilities (Monthly) | C43: 500 | D43: =C43*12 -> 6000 | E43: =C43*12 -> 6000 | F43: =C43*12 -> 6000
B44: Insurance (Annual) | C44: 3000 | D44: =C44 -> 3000 | E44: =C44 -> 3000 | F44: =C44 -> 3000
B45: Property Tax — from Zillow listing | C45: from listing | D45: 0 | E45: =D45 -> 0 | F45: =D45 -> 0
B46: Maintenance Reserve — Annual (by beds) | C46: =IF(D6>=8,800,IF(D6=7,700,IF(D6=6,500,400))) -> 500 | D46: =C46 -> 500 | E46: =C46 -> 500 | F46: =C46 -> 500
B47: Lawn / Snow (Monthly) | C47: 150 | D47: =C47*12 -> 1800 | E47: =C47*12 -> 1800 | F47: =C47*12 -> 1800
B48: Pest Control (Annual) | C48: 150 | D48: =C48 -> 150 | E48: =C48 -> 150 | F48: =C48 -> 150
B49: Hot Tub / Pool (Monthly) | C49: 200 | D49: =C49*12 -> 2400 | E49: =C49*12 -> 2400 | F49: =C49*12 -> 2400
B50: Software (Monthly) | C50: 150 | D50: =C50*12 -> 1800 | E50: =C50*12 -> 1800 | F50: =C50*12 -> 1800
B51: Mortgage Insurance (Annual) | D51: =D19 -> 3825 | E51: =D19 -> 3825 | F51: =D19 -> 3825
B52: Permits & Licenses (Annual) | C52: 0 | D52: =C52 -> 0 | E52: =C52 -> 0 | F52: =C52 -> 0
B53: Total Operating Expenses | D53: =D39+D40+D41+D42+D43+D44+D45+D46+D47+D48+D49+D50+D51+D52 -> 57365.025 | E53: =E39+E40+E41+E42+E43+E44+E45+E46+E47+E48+E49+E50+E51+E52 -> 64909.438 | F53: =F39+F40+F41+F42+F43+F44+F45+F46+F47+F48+F49+F50+F51+F52 -> 72641.5
B54: OpEx Ratio | D54: =D53/D33 -> 0.98535707 | E54: =E53/E33 -> 0.84181811 | F54: =F53/F33 -> 0.73710299
B56: INCOME STATEMENT
B57: Gross Revenue | D57: =D33 -> 58217.5 | E57: =E33 -> 77106.25 | F57: =F33 -> 98550
B58: Total Operating Expenses | D58: =-D53 -> -57365.025 | E58: =-E53 -> -64909.438 | F58: =-F53 -> -72641.5
B59: Net Operating Income (NOI) | D59: =D57+D58 -> 852.475 | E59: =E57+E58 -> 12196.812 | F59: =F57+F58 -> 25908.5
B60: Annual Debt Service | D60: =-D21 -> -61074.769 | E60: =-D21 -> -61074.769 | F60: =-D21 -> -61074.769
B61: Free Cash Flow (Annual) | D61: =D59-D21 -> -60222.294 | E61: =E59-D21 -> -48877.957 | F61: =F59-D21 -> -35166.269
B62: Monthly Cash Flow (Avg) | D62: =D61/12 -> -5018.5245 | E62: =E61/12 -> -4073.163 | F62: =F61/12 -> -2930.5224
B63: Cash-on-Cash Return | D63: =D61/D28 -> -0.54499814 | E63: =E61/D28 -> -0.44233445 | F63: =F61/D28 -> -0.31824678
B64: Gross Yield | D64: =D33/D12 -> 0.068491176 | E64: =E33/D12 -> 0.090713235 | F64: =F33/D12 -> 0.11594118
B65: Rating (based on Mid CoC) | E65: =IF(E63>=0.1,"✓ STRONG BUY",IF(E63>=0.08,"BUY",IF(E63>=0.06,"HOLD","✗ PASS"))) -> ✗ PASS
B67: TAX & DEPRECIATION (Federal Only — CA does not conform)
B68: Depreciable Basis (excl. land @ 20%) | C68: 0.8 | D68: =D12*C68 -> 680000
B69: Personal Property (25%) — 5-yr MACRS | C69: 0.25 | D69: =D68*C69 -> 170000
B70: Land Improvements (15%) — 15-yr MACRS | C70: 0.15 | D70: =D68*C70 -> 102000
B71: Building (40%) — 39-yr Straight Line | C71: 0.4 | D71: =D68*C71 -> 272000
B72: Bonus Depreciation Rate (2026: 20%) | C72: 0.2
B73: Year 1 Bonus Depreciation (5-yr + 15-yr components) | D73: =(D69+D70)*C72 -> 54400
B74: Straight-Line Depreciation — Building (Annual) | D74: =D71/39 -> 6974.359
B75: Total Year 1 Depreciation Deduction | D75: =D73+D74 -> 61374.359
B76: Federal Tax Rate | C76: 0.37
B77: Federal Tax Savings — Year 1 | D77: =D75*C76 -> 22708.513
B78: Note: No CA state tax savings modeled — CA does not allow STR losses to offset state income.
B80: TOTAL RETURN SUMMARY — YEAR 1 (Hold Forever, No Planned Exit)
B81: Net Cash Flow | D81: =D61 -> -60222.294 | E81: =E61 -> -48877.957 | F81: =F61 -> -35166.269
B82: Federal Tax Savings (Depreciation) | D82: =D77 -> 22708.513 | E82: =D77 -> 22708.513 | F82: =D77 -> 22708.513
B83: Appreciation (0% conservative baseline) | C83: 0 | D83: =D12*C83 -> 0 | E83: =D12*C83 -> 0 | F83: =D12*C83 -> 0
B84: Mortgage Paydown — Principal (Year 1) | D84: =D22 -> 7524.7691 | E84: =D22 -> 7524.7691 | F84: =D22 -> 7524.7691
B85: Total Return — Year 1 ($) | D85: =D81+D82+D83+D84 -> -29989.012 | E85: =E81+E82+E83+E84 -> -18644.675 | F85: =F81+F82+F83+F84 -> -4932.9872
B86: Total Return % (of Cash Invested) | D86: =D85/D28 -> -0.27139378 | E86: =E85/D28 -> -0.16873009 | F86: =F85/D28 -> -0.044642418

Sheet long_term_ROI
B1: STR LONG-TERM ROI — 10-YEAR HOLD (Mid Scenario)
B2: Address: | C2: =underwriting!D2 -> {{address}}
C4: Year 1 | D4: Year 2 | E4: Year 3 | F4: Year 4 | G4: Year 5 | H4: Year 6 | I4: Year 7 | J4: Year 8 | K4: Year 9 | L4: Year 10
B6: ASSUMPTIONS
B7: Annual Cash Flow (Mid) | C7: =underwriting!E61 -> -48877.957 | D7: =underwriting!E61 -> -48877.957 | E7: =underwriting!E61 -> -48877.957 | F7: =underwriting!E61 -> -48877.957 | G7: =underwriting!E61 -> -48877.957 | H7: =underwriting!E61 -> -48877.957 | I7: =underwriting!E61 -> -48877.957 | J7: =underwriting!E61 -> -48877.957 | K7: =underwriting!E61 -> -48877.957 | L7: =underwriting!E61 -> -48877.957
B8: Federal Tax Savings (Yr 1 bonus, then SL) | C8: =underwriting!D77 -> 22708.513 | D8: =underwriting!D74*underwriting!C76 -> 2580.5128 | E8: =underwriting!D74*underwriting!C76 -> 2580.5128 | F8: =underwriting!D74*underwriting!C76 -> 2580.5128 | G8: =underwriting!D74*underwriting!C76 -> 2580.5128 | H8: =underwriting!D74*underwriting!C76 -> 2580.5128 | I8: =underwriting!D74*underwriting!C76 -> 2580.5128 | J8: =underwriting!D74*underwriting!C76 -> 2580.5128 | K8: =underwriting!D74*underwriting!C76 -> 2580.5128 | L8: =underwriting!D74*underwriting!C76 -> 2580.5128
B9: Appreciation Rate | C9: 0
B10: Purchase Price | C10: =underwriting!D12 -> 850000
B12: CUMULATIVE RETURN COMPONENTS (Mid Scenario)
B13: Annual Cash Flow | C13: =underwriting!E61 -> -48877.957 | D13: =underwriting!E61 -> -48877.957 | E13: =underwriting!E61 -> -48877.957 | F13: =underwriting!E61 -> -48877.957 | G13: =underwriting!E61 -> -48877.957 | H13: =underwriting!E61 -> -48877.957 | I13: =underwriting!E61 -> -48877.957 | J13: =underwriting!E61 -> -48877.957 | K13: =underwriting!E61 -> -48877.957 | L13: =underwriting!E61 -> -48877.957
B14: Cumulative Cash Flow | C14: =C13 -> -48877.957 | D14: =C14+D13 -> -97755.913 | E14: =D14+E13 -> -146633.87 | F14: =E14+F13 -> -195511.83 | G14: =F14+G13 -> -244389.78 | H14: =G14+H13 -> -293267.74 | I14: =H14+I13 -> -342145.7 | J14: =I14+J13 -> -391023.65 | K14: =J14+K13 -> -439901.61 | L14: =K14+L13 -> -488779.57
B15: Annual Tax Savings | C15: =underwriting!D77 -> 22708.513 | D15: =underwriting!D74*underwriting!C76 -> 2580.5128 | E15: =underwriting!D74*underwriting!C76 -> 2580.5128 | F15: =underwriting!D74*underwriting!C76 -> 2580.5128 | G15: =underwriting!D74*underwriting!C76 -> 2580.5128 | H15: =underwriting!D74*underwriting!C76 -> 2580.5128 | I15: =underwriting!D74*underwriting!C76 -> 2580.5128 | J15: =underwriting!D74*underwriting!C76 -> 2580.5128 | K15: =underwriting!D74*underwriting!C76 -> 2580.5128 | L15: =underwriting!D74*underwriting!C76 -> 2580.5128
B16: Cumulative Tax Savings | C16: =C15 -> 22708.513 | D16: =C16+D15 -> 25289.026 | E16: =D16+E15 -> 27869.538 | F16: =E16+F15 -> 30450.051 | G16: =F16+G15 -> 33030.564 | H16: =G16+H15 -> 35611.077 | I16: =H16+I15 -> 38191.59 | J16: =I16+J15 -> 40772.103 | K16: =J16+K15 -> 43352.615 | L16: =K16+L15 -> 45933.128
B17: Annual Appreciation (0% baseline) | C17: =underwriting!D12*$C$9 -> 0 | D17: =underwriting!D12*$C$9 -> 0 | E17: =underwriting!D12*$C$9 -> 0 | F17: =underwriting!D12*$C$9 -> 0 | G17: =underwriting!D12*$C$9 -> 0 | H17: =underwriting!D12*$C$9 -> 0 | I17: =underwriting!D12*$C$9 -> 0 | J17: =underwriting!D12*$C$9 -> 0 | K17: =underwriting!D12*$C$9 -> 0 | L17: =underwriting!D12*$C$9 -> 0
B18: Cumulative Appreciation | C18: =C17 -> 0 | D18: =C18+D17 -> 0 | E18: =D18+E17 -> 0 | F18: =E18+F17 -> 0 | G18: =F18+G17 -> 0 | H18: =G18+H17 -> 0 | I18: =H18+I17 -> 0 | J18: =I18+J17 -> 0 | K18: =J18+K17 -> 0 | L18: =K18+L17 -> 0
B19: Annual Principal Paydown (approx.) | C19: =underwriting!D22 -> 7524.7691 | D19: =underwriting!D22 -> 7524.7691 | E19: =underwriting!D22 -> 7524.7691 | F19: =underwriting!D22 -> 7524.7691 | G19: =underwriting!D22 -> 7524.7691 | H19: =underwriting!D22 -> 7524.7691 | I19: =underwriting!D22 -> 7524.7691 | J19: =underwriting!D22 -> 7524.7691 | K19: =underwriting!D22 -> 7524.7691 | L19: =underwriting!D22 -> 7524.7691
B20: Cumulative Principal Paydown | C20: =C19 -> 7524.7691 | D20: =C20+D19 -> 15049.538 | E20: =D20+E19 -> 22574.307 | F20: =E20+F19 -> 30099.076 | G20: =F20+G19 -> 37623.845 | H20: =G20+H19 -> 45148.614 | I20: =H20+I19 -> 52673.383 | J20: =I20+J19 -> 60198.152 | K20: =J20+K19 -> 67722.922 | L20: =K20+L19 -> 75247.691
B22: TOTAL CUMULATIVE RETURN ($) | C22: =C14+C16+C18+C20 -> -18644.675 | D22: =D14+D16+D18+D20 -> -57417.349 | E22: =E14+E16+E18+E20 -> -96190.024 | F22: =F14+F16+F18+F20 -> -134962.7 | G22: =G14+G16+G18+G20 -> -173735.37 | H22: =H14+H16+H18+H20 -> -212508.05 | I22: =I14+I16+I18+I20 -> -251280.72 | J22: =J14+J16+J18+J20 -> -290053.4 | ... L22: =L14+L16+L18+L20 -> -367598.75
B23: TOTAL RETURN % (of Cash Invested) | C23: =C22/underwriting!D28 -> -0.16873009 | D23: =D22/underwriting!D28 -> -0.51961402 | E23: =E22/underwriting!D28 -> -0.87049796 | F23: =F22/underwriting!D28 -> -1.2213819 | G23: =G22/underwriting!D28 -> -1.5722658 | H23: =H22/underwriting!D28 -> -1.9231498 | I23: =I22/underwriting!D28 -> -2.2740337 | J23: =J22/underwriting!D28 -> -2.6249176 | K23: =K22/underwriting!D28 -> -2.9758016 | L23: =L22/underwriting!D28 -> -3.3266855
B24: Cash-on-Cash (annual, Mid) | C24: =underwriting!E63 -> -0.44233445 | D24: =underwriting!E63 -> -0.44233445 | E24: =underwriting!E63 -> -0.44233445 | F24: =underwriting!E63 -> -0.44233445 | G24: =underwriting!E63 -> -0.44233445 | H24: =underwriting!E63 -> -0.44233445 | I24: =underwriting!E63 -> -0.44233445 | J24: =underwriting!E63 -> -0.44233445 | K24: =underwriting!E63 -> -0.44233445 | L24: =underwriting!E63 -> -0.44233445

Sheet amortization
B1: MORTGAGE AMORTIZATION TABLE
B2: Loan Amount | C2: =underwriting!D14 -> 765000
B3: Interest Rate | C3: =underwriting!C15 -> 0.07
B4: Term (Years) | C4: =underwriting!C16 -> 30
B5: Monthly Payment | C5: =underwriting!D20 -> 5089.5641
B7: Month | C7: Beg. Balance | D7: Payment | E7: Interest | F7: Principal | G7: End Balance | H7: Cum. Paydown
B8: 1 | C8: =underwriting!D14 -> 765000 | D8: =underwriting!D20 -> 5089.5641 | E8: =C8*underwriting!C15/12 -> 4462.5 | F8: =D8-E8 -> 627.06409 | G8: =C8-F8 -> 764372.94 | H8: =F8 -> 627.06409
B9: 2 | C9: =G8 -> 764372.94 | D9: =underwriting!D20 -> 5089.5641 | E9: =C9*underwriting!C15/12 -> 4458.8421 | F9: =D9-E9 -> 630.72196 | G9: =C9-F9 -> 763742.21 | H9: =H8+F9 -> 1257.7861
B10: 3 | C10: =G9 -> 763742.21 | D10: =underwriting!D20 -> 5089.5641 | E10: =C10*underwriting!C15/12 -> 4455.1629 | F10: =D10-E10 -> 634.40117 | G10: =C10-F10 -> 763107.81 | H10: =H9+F10 -> 1892.1872
B11: 4 | C11: =G10 -> 763107.81 | D11: =underwriting!D20 -> 5089.5641 | E11: =C11*underwriting!C15/12 -> 4451.4622 | F11: =D11-E11 -> 638.10185 | G11: =C11-F11 -> 762469.71 | H11: =H10+F11 -> 2530.2891
B12: 5 | C12: =G11 -> 762469.71 | D12: =underwriting!D20 -> 5089.5641 | E12: =C12*underwriting!C15/12 -> 4447.74 | F12: =D12-E12 -> 641.82411 | G12: =C12-F12 -> 761827.89 | H12: =H11+F12 -> 3172.1132
B13: 6 | C13: =G12 -> 761827.89 | D13: =underwriting!D20 -> 5089.5641 | E13: =C13*underwriting!C15/12 -> 4443.996 | F13: =D13-E13 -> 645.56808 | G13: =C13-F13 -> 761182.32 | H13: =H12+F13 -> 3817.6813
B14: 7 | C14: =G13 -> 761182.32 | D14: =underwriting!D20 -> 5089.5641 | E14: =C14*underwriting!C15/12 -> 4440.2302 | F14: =D14-E14 -> 649.3339 | G14: =C14-F14 -> 760532.98 | H14: =H13+F14 -> 4467.0152
B15: 8 | C15: =G14 -> 760532.98 | D15: =underwriting!D20 -> 5089.5641 | E15: =C15*underwriting!C15/12 -> 4436.4424 | F15: =D15-E15 -> 653.12168 | G15: =C15-F15 -> 759879.86 | H15: =H14+F15 -> 5120.1368
B16: 9 | C16: =G15 -> 759879.86 | D16: =underwriting!D20 -> 5089.5641 | E16: =C16*underwriting!C15/12 -> 4432.6325 | F16: =D16-E16 -> 656.93155 | G16: =C16-F16 -> 759222.93 | H16: =H15+F16 -> 5777.0684
B17: 10 | C17: =G16 -> 759222.93 | D17: =underwriting!D20 -> 5089.5641 | E17: =C17*underwriting!C15/12 -> 4428.8004 | F17: =D17-E17 -> 660.76365 | G17: =C17-F17 -> 758562.17 | H17: =H16+F17 -> 6437.832
B18: 11 | C18: =G17 -> 758562.17 | D18: =underwriting!D20 -> 5089.5641 | E18: =C18*underwriting!C15/12 -> 4424.946 | F18: =D18-E18 -> 664.61811 | G18: =C18-F18 -> 757897.55 | H18: =H17+F18 -> 7102.4501
B19: 12 | C19: =G18 -> 757897.55 | D19: =underwriting!D20 -> 5089.5641 | E19: =C19*underwriting!C15/12 -> 4421.069 | F19: =D19-E19 -> 668.49505 | G19: =C19-F19 -> 757229.05 | H19: =H18+F19 -> 7770.9452
B20: 13 | C20: =G19 -> 757229.05 | D20: =underwriting!D20 -> 5089.5641 | E20: =C20*underwriting!C15/12 -> 4417.1695 | F20: =D20-E20 -> 672.3946 | G20: =C20-F20 -> 756556.66 | H20: =H19+F20 -> 8443.3398
B21: 14 | C21: =G20 -> 756556.66 | D21: =underwriting!D20 -> 5089.5641 | E21: =C21*underwriting!C15/12 -> 4413.2472 | F21: =D21-E21 -> 676.3169 | G21: =C21-F21 -> 755880.34 | H21: =H20+F21 -> 9119.6567
B22: 15 | C22: =G21 -> 755880.34 | D22: =underwriting!D20 -> 5089.5641 | E22: =C22*underwriting!C15/12 -> 4409.302 | F22: =D22-E22 -> 680.26209 | G22: =C22-F22 -> 755200.08 | H22: =H21+F22 -> 9799.9188
B23: 16 | C23: =G22 -> 755200.08 | D23: =underwriting!D20 -> 5089.5641 | E23: =C23*underwriting!C15/12 -> 4405.3338 | F23: =D23-E23 -> 684.23028 | G23: =C23-F23 -> 754515.85 | H23: =H22+F23 -> 10484.149
B24: 17 | C24: =G23 -> 754515.85 | D24: =underwriting!D20 -> 5089.5641 | E24: =C24*underwriting!C15/12 -> 4401.3425 | F24: =D24-E24 -> 688.22162 | G24: =C24-F24 -> 753827.63 | H24: =H23+F24 -> 11172.371
B25: 18 | C25: =G24 -> 753827.63 | D25: =underwriting!D20 -> 5089.5641 | E25: =C25*underwriting!C15/12 -> 4397.3278 | F25: =D25-E25 -> 692.23625 | G25: =C25-F25 -> 753135.39 | H25: =H24+F25 -> 11864.607
B26: 19 | C26: =G25 -> 753135.39 | D26: =underwriting!D20 -> 5089.5641 | E26: =C26*underwriting!C15/12 -> 4393.2898 | F26: =D26-E26 -> 696.2743 | G26: =C26-F26 -> 752439.12 | H26: =H25+F26 -> 12560.881
B27: 20 | C27: =G26 -> 752439.12 | D27: =underwriting!D20 -> 5089.5641 | E27: =C27*underwriting!C15/12 -> 4389.2282 | F27: =D27-E27 -> 700.3359 | G27: =C27-F27 -> 751738.78 | H27: =H26+F27 -> 13261.217
B28: 21 | C28: =G27 -> 751738.78 | D28: =underwriting!D20 -> 5089.5641 | E28: =C28*underwriting!C15/12 -> 4385.1429 | F28: =D28-E28 -> 704.42119 | G28: =C28-F28 -> 751034.36 | H28: =H27+F28 -> 13965.638
B29: 22 | C29: =G28 -> 751034.36 | D29: =underwriting!D20 -> 5089.5641 | E29: =C29*underwriting!C15/12 -> 4381.0338 | F29: =D29-E29 -> 708.53031 | G29: =C29-F29 -> 750325.83 | H29: =H28+F29 -> 14674.169
B30: 23 | C30: =G29 -> 750325.83 | D30: =underwriting!D20 -> 5089.5641 | E30: =C30*underwriting!C15/12 -> 4376.9007 | F30: =D30-E30 -> 712.66341 | G30: =C30-F30 -> 749613.17 | H30: =H29+F30 -> 15386.832
B31: 24 | C31: =G30 -> 749613.17 | D31: =underwriting!D20 -> 5089.5641 | E31: =C31*underwriting!C15/12 -> 4372.7435 | F31: =D31-E31 -> 716.82061 | G31: =C31-F31 -> 748896.35 | H31: =H30+F31 -> 16103.653
B32: 25 | C32: =G31 -> 748896.35 | D32: =underwriting!D20 -> 5089.5641 | E32: =C32*underwriting!C15/12 -> 4368.562 | F32: =D32-E32 -> 721.00206 | G32: =C32-F32 -> 748175.35 | H32: =H31+F32 -> 16824.655
B33: 26 | C33: =G32 -> 748175.35 | D33: =underwriting!D20 -> 5089.5641 | E33: =C33*underwriting!C15/12 -> 4364.3562 | F33: =D33-E33 -> 725.20791 | G33: =C33-F33 -> 747450.14 | H33: =H32+F33 -> 17549.863
B34: 27 | C34: =G33 -> 747450.14 | D34: =underwriting!D20 -> 5089.5641 | E34: =C34*underwriting!C15/12 -> 4360.1258 | F34: =D34-E34 -> 729.43829 | G34: =C34-F34 -> 746720.7 | H34: =H33+F34 -> 18279.301
B35: 28 | C35: =G34 -> 746720.7 | D35: =underwriting!D20 -> 5089.5641 | E35: =C35*underwriting!C15/12 -> 4355.8707 | F35: =D35-E35 -> 733.69334 | G35: =C35-F35 -> 745987.01 | H35: =H34+F35 -> 19012.994
B36: 29 | C36: =G35 -> 745987.01 | D36: =underwriting!D20 -> 5089.5641 | E36: =C36*underwriting!C15/12 -> 4351.5909 | F36: =D36-E36 -> 737.97322 | G36: =C36-F36 -> 745249.03 | H36: =H35+F36 -> 19750.967
B37: 30 | C37: =G36 -> 745249.03 | D37: =underwriting!D20 -> 5089.5641 | E37: =C37*underwriting!C15/12 -> 4347.286 | F37: =D37-E37 -> 742.27807 | G37: =C37-F37 -> 744506.75 | H37: =H36+F37 -> 20493.246
B38: 31 | C38: =G37 -> 744506.75 | D38: =underwriting!D20 -> 5089.5641 | E38: =C38*underwriting!C15/12 -> 4342.9561 | F38: =D38-E38 -> 746.60802 | G38: =C38-F38 -> 743760.15 | H38: =H37+F38 -> 21239.854
B39: 32 | C39: =G38 -> 743760.15 | D39: =underwriting!D20 -> 5089.5641 | E39: =C39*underwriting!C15/12 -> 4338.6009 | F39: =D39-E39 -> 750.96323 | G39: =C39-F39 -> 743009.18 | H39: =H38+F39 -> 21990.817
B40: 33 | C40: =G39 -> 743009.18 | D40: =underwriting!D20 -> 5089.5641 | E40: =C40*underwriting!C15/12 -> 4334.2202 | F40: =D40-E40 -> 755.34385 | G40: =C40-F40 -> 742253.84 | H40: =H39+F40 -> 22746.161
B41: 34 | C41: =G40 -> 742253.84 | D41: =underwriting!D20 -> 5089.5641 | E41: =C41*underwriting!C15/12 -> 4329.8141 | F41: =D41-E41 -> 759.75003 | G41: =C41-F41 -> 741494.09 | H41: =H40+F41 -> 23505.911
B42: 35 | C42: =G41 -> 741494.09 | D42: =underwriting!D20 -> 5089.5641 | E42: =C42*underwriting!C15/12 -> 4325.3822 | F42: =D42-E42 -> 764.1819 | G42: =C42-F42 -> 740729.91 | H42: =H41+F42 -> 24270.093
B43: 36 | C43: =G42 -> 740729.91 | D43: =underwriting!D20 -> 5089.5641 | E43: =C43*underwriting!C15/12 -> 4320.9245 | F43: =D43-E43 -> 768.63963 | G43: =C43-F43 -> 739961.27 | H43: =H42+F43 -> 25038.732
B44: 37 | C44: =G43 -> 739961.27 | D44: =underwriting!D20 -> 5089.5641 | E44: =C44*underwriting!C15/12 -> 4316.4407 | F44: =D44-E44 -> 773.12336 | G44: =C44-F44 -> 739188.14 | H44: =H43+F44 -> 25811.856
B45: 38 | C45: =G44 -> 739188.14 | D45: =underwriting!D20 -> 5089.5641 | E45: =C45*underwriting!C15/12 -> 4311.9308 | F45: =D45-E45 -> 777.63325 | G45: =C45-F45 -> 738410.51 | H45: =H44+F45 -> 26589.489
B46: 39 | C46: =G45 -> 738410.51 | D46: =underwriting!D20 -> 5089.5641 | E46: =C46*underwriting!C15/12 -> 4307.3946 | F46: =D46-E46 -> 782.16944 | G46: =C46-F46 -> 737628.34 | H46: =H45+F46 -> 27371.658
B47: 40 | C47: =G46 -> 737628.34 | D47: =underwriting!D20 -> 5089.5641 | E47: =C47*underwriting!C15/12 -> 4302.832 | F47: =D47-E47 -> 786.73209 | G47: =C47-F47 -> 736841.61 | H47: =H46+F47 -> 28158.39
B48: 41 | C48: =G47 -> 736841.61 | D48: =underwriting!D20 -> 5089.5641 | E48: =C48*underwriting!C15/12 -> 4298.2427 | F48: =D48-E48 -> 791.32137 | G48: =C48-F48 -> 736050.29 | H48: =H47+F48 -> 28949.712
B49: 42 | C49: =G48 -> 736050.29 | D49: =underwriting!D20 -> 5089.5641 | E49: =C49*underwriting!C15/12 -> 4293.6267 | F49: =D49-E49 -> 795.93741 | G49: =C49-F49 -> 735254.35 | H49: =H48+F49 -> 29745.649
B50: 43 | C50: =G49 -> 735254.35 | D50: =underwriting!D20 -> 5089.5641 | E50: =C50*underwriting!C15/12 -> 4288.9837 | F50: =D50-E50 -> 800.58037 | G50: =C50-F50 -> 734453.77 | H50: =H49+F50 -> 30546.229
B51: 44 | C51: =G50 -> 734453.77 | D51: =underwriting!D20 -> 5089.5641 | E51: =C51*underwriting!C15/12 -> 4284.3137 | F51: =D51-E51 -> 805.25043 | G51: =C51-F51 -> 733648.52 | H51: =H50+F51 -> 31351.48
B52: 45 | C52: =G51 -> 733648.52 | D52: =underwriting!D20 -> 5089.5641 | E52: =C52*underwriting!C15/12 -> 4279.6164 | F52: =D52-E52 -> 809.94772 | G52: =C52-F52 -> 732838.57 | H52: =H51+F52 -> 32161.428
B53: 46 | C53: =G52 -> 732838.57 | D53: =underwriting!D20 -> 5089.5641 | E53: =C53*underwriting!C15/12 -> 4274.8917 | F53: =D53-E53 -> 814.67242 | G53: =C53-F53 -> 732023.9 | H53: =H52+F53 -> 32976.1
B54: 47 | C54: =G53 -> 732023.9 | D54: =underwriting!D20 -> 5089.5641 | E54: =C54*underwriting!C15/12 -> 4270.1394 | F54: =D54-E54 -> 819.42467 | G54: =C54-F54 -> 731204.48 | H54: =H53+F54 -> 33795.525
B55: 48 | C55: =G54 -> 731204.48 | D55: =underwriting!D20 -> 5089.5641 | E55: =C55*underwriting!C15/12 -> 4265.3594 | F55: =D55-E55 -> 824.20465 | G55: =C55-F55 -> 730380.27 | H55: =H54+F55 -> 34619.729
B56: 49 | C56: =G55 -> 730380.27 | D56: =underwriting!D20 -> 5089.5641 | E56: =C56*underwriting!C15/12 -> 4260.5516 | F56: =D56-E56 -> 829.01251 | G56: =C56-F56 -> 729551.26 | H56: =H55+F56 -> 35448.742
B57: 50 | C57: =G56 -> 729551.26 | D57: =underwriting!D20 -> 5089.5641 | E57: =C57*underwriting!C15/12 -> 4255.7157 | F57: =D57-E57 -> 833.84842 | G57: =C57-F57 -> 728717.41 | H57: =H56+F57 -> 36282.59
B58: 51 | C58: =G57 -> 728717.41 | D58: =underwriting!D20 -> 5089.5641 | E58: =C58*underwriting!C15/12 -> 4250.8516 | F58: =D58-E58 -> 838.71253 | G58: =C58-F58 -> 727878.7 | H58: =H57+F58 -> 37121.303
B59: 52 | C59: =G58 -> 727878.7 | D59: =underwriting!D20 -> 5089.5641 | E59: =C59*underwriting!C15/12 -> 4245.9591 | F59: =D59-E59 -> 843.60502 | G59: =C59-F59 -> 727035.09 | H59: =H58+F59 -> 37964.908
B60: 53 | C60: =G59 -> 727035.09 | D60: =underwriting!D20 -> 5089.5641 | E60: =C60*underwriting!C15/12 -> 4241.038 | F60: =D60-E60 -> 848.52605 | G60: =C60-F60 -> 726186.57 | H60: =H59+F60 -> 38813.434
B61: 54 | C61: =G60 -> 726186.57 | D61: =underwriting!D20 -> 5089.5641 | E61: =C61*underwriting!C15/12 -> 4236.0883 | F61: =D61-E61 -> 853.47579 | G61: =C61-F61 -> 725333.09 | H61: =H60+F61 -> 39666.91
B62: 55 | C62: =G61 -> 725333.09 | D62: =underwriting!D20 -> 5089.5641 | E62: =C62*underwriting!C15/12 -> 4231.1097 | F62: =D62-E62 -> 858.45439 | G62: =C62-F62 -> 724474.64 | H62: =H61+F62 -> 40525.364
B63: 56 | C63: =G62 -> 724474.64 | D63: =underwriting!D20 -> 5089.5641 | E63: =C63*underwriting!C15/12 -> 4226.102 | F63: =D63-E63 -> 863.46205 | G63: =C63-F63 -> 723611.17 | H63: =H62+F63 -> 41388.826
B64: 57 | C64: =G63 -> 723611.17 | D64: =underwriting!D20 -> 5089.5641 | E64: =C64*underwriting!C15/12 -> 4221.0652 | F64: =D64-E64 -> 868.49891 | G64: =C64-F64 -> 722742.67 | H64: =H63+F64 -> 42257.325
B65: 58 | C65: =G64 -> 722742.67 | D65: =underwriting!D20 -> 5089.5641 | E65: =C65*underwriting!C15/12 -> 4215.9989 | F65: =D65-E65 -> 873.56515 | G65: =C65-F65 -> 721869.11 | H65: =H64+F65 -> 43130.89
B66: 59 | C66: =G65 -> 721869.11 | D66: =underwriting!D20 -> 5089.5641 | E66: =C66*underwriting!C15/12 -> 4210.9031 | F66: =D66-E66 -> 878.66095 | G66: =C66-F66 -> 720990.45 | H66: =H65+F66 -> 44009.551
B67: 60 | C67: =G66 -> 720990.45 | D67: =underwriting!D20 -> 5089.5641 | E67: =C67*underwriting!C15/12 -> 4205.7776 | F67: =D67-E67 -> 883.78647 | G67: =C67-F67 -> 720106.66 | H67: =H66+F67 -> 44893.338
B68: 61 | C68: =G67 -> 720106.66 | D68: =underwriting!D20 -> 5089.5641 | E68: =C68*underwriting!C15/12 -> 4200.6222 | F68: =D68-E68 -> 888.94189 | G68: =C68-F68 -> 719217.72 | H68: =H67+F68 -> 45782.279
B69: 62 | C69: =G68 -> 719217.72 | D69: =underwriting!D20 -> 5089.5641 | E69: =C69*underwriting!C15/12 -> 4195.4367 | F69: =D69-E69 -> 894.12739 | G69: =C69-F69 -> 718323.59 | H69: =H68+F69 -> 46676.407
B70: 63 | C70: =G69 -> 718323.59 | D70: =underwriting!D20 -> 5089.5641 | E70: =C70*underwriting!C15/12 -> 4190.221 | F70: =D70-E70 -> 899.34313 | G70: =C70-F70 -> 717424.25 | H70: =H69+F70 -> 47575.75
B71: 64 | C71: =G70 -> 717424.25 | D71: =underwriting!D20 -> 5089.5641 | E71: =C71*underwriting!C15/12 -> 4184.9748 | F71: =D71-E71 -> 904.5893 | G71: =C71-F71 -> 716519.66 | H71: =H70+F71 -> 48480.339
B72: 65 | C72: =G71 -> 716519.66 | D72: =underwriting!D20 -> 5089.5641 | E72: =C72*underwriting!C15/12 -> 4179.698 | F72: =D72-E72 -> 909.86607 | G72: =C72-F72 -> 715609.79 | H72: =H71+F72 -> 49390.205
B73: 66 | C73: =G72 -> 715609.79 | D73: =underwriting!D20 -> 5089.5641 | E73: =C73*underwriting!C15/12 -> 4174.3905 | F73: =D73-E73 -> 915.17362 | G73: =C73-F73 -> 714694.62 | H73: =H72+F73 -> 50305.379
B74: 67 | C74: =G73 -> 714694.62 | D74: =underwriting!D20 -> 5089.5641 | E74: =C74*underwriting!C15/12 -> 4169.052 | F74: =D74-E74 -> 920.51213 | G74: =C74-F74 -> 713774.11 | H74: =H73+F74 -> 51225.891
B75: 68 | C75: =G74 -> 713774.11 | D75: =underwriting!D20 -> 5089.5641 | E75: =C75*underwriting!C15/12 -> 4163.6823 | F75: =D75-E75 -> 925.88179 | G75: =C75-F75 -> 712848.23 | H75: =H74+F75 -> 52151.773
B76: 69 | C76: =G75 -> 712848.23 | D76: =underwriting!D20 -> 5089.5641 | E76: =C76*underwriting!C15/12 -> 4158.2813 | F76: =D76-E76 -> 931.28276 | G76: =C76-F76 -> 711916.94 | H76: =H75+F76 -> 53083.056
B77: 70 | C77: =G76 -> 711916.94 | D77: =underwriting!D20 -> 5089.5641 | E77: =C77*underwriting!C15/12 -> 4152.8488 | F77: =D77-E77 -> 936.71525 | G77: =C77-F77 -> 710980.23 | H77: =H76+F77 -> 54019.771
B78: 71 | C78: =G77 -> 710980.23 | D78: =underwriting!D20 -> 5089.5641 | E78: =C78*underwriting!C15/12 -> 4147.3847 | F78: =D78-E78 -> 942.17942 | G78: =C78-F78 -> 710038.05 | H78: =H77+F78 -> 54961.95
B79: 72 | C79: =G78 -> 710038.05 | D79: =underwriting!D20 -> 5089.5641 | E79: =C79*underwriting!C15/12 -> 4141.8886 | F79: =D79-E79 -> 947.67546 | G79: =C79-F79 -> 709090.37 | H79: =H78+F79 -> 55909.626
B80: 73 | C80: =G79 -> 709090.37 | D80: =underwriting!D20 -> 5089.5641 | E80: =C80*underwriting!C15/12 -> 4136.3605 | F80: =D80-E80 -> 953.20357 | G80: =C80-F80 -> 708137.17 | H80: =H79+F80 -> 56862.829
B81: 74 | C81: =G80 -> 708137.17 | D81: =underwriting!D20 -> 5089.5641 | E81: =C81*underwriting!C15/12 -> 4130.8002 | F81: =D81-E81 -> 958.76393 | G81: =C81-F81 -> 707178.41 | H81: =H80+F81 -> 57821.593
B82: 75 | C82: =G81 -> 707178.41 | D82: =underwriting!D20 -> 5089.5641 | E82: =C82*underwriting!C15/12 -> 4125.2074 | F82: =D82-E82 -> 964.35672 | G82: =C82-F82 -> 706214.05 | H82: =H81+F82 -> 58785.95
B83: 76 | C83: =G82 -> 706214.05 | D83: =underwriting!D20 -> 5089.5641 | E83: =C83*underwriting!C15/12 -> 4119.582 | F83: =D83-E83 -> 969.98213 | G83: =C83-F83 -> 705244.07 | H83: =H82+F83 -> 59755.932
B84: 77 | C84: =G83 -> 705244.07 | D84: =underwriting!D20 -> 5089.5641 | E84: =C84*underwriting!C15/12 -> 4113.9237 | F84: =D84-E84 -> 975.64036 | G84: =C84-F84 -> 704268.43 | H84: =H83+F84 -> 60731.572
B85: 78 | C85: =G84 -> 704268.43 | D85: =underwriting!D20 -> 5089.5641 | E85: =C85*underwriting!C15/12 -> 4108.2325 | F85: =D85-E85 -> 981.33159 | G85: =C85-F85 -> 703287.1 | H85: =H84+F85 -> 61712.904
B86: 79 | C86: =G85 -> 703287.1 | D86: =underwriting!D20 -> 5089.5641 | E86: =C86*underwriting!C15/12 -> 4102.5081 | F86: =D86-E86 -> 987.05603 | G86: =C86-F86 -> 702300.04 | H86: =H85+F86 -> 62699.96
B87: 80 | C87: =G86 -> 702300.04 | D87: =underwriting!D20 -> 5089.5641 | E87: =C87*underwriting!C15/12 -> 4096.7502 | F87: =D87-E87 -> 992.81386 | G87: =C87-F87 -> 701307.23 | H87: =H86+F87 -> 63692.774
B88: 81 | C88: =G87 -> 701307.23 | D88: =underwriting!D20 -> 5089.5641 | E88: =C88*underwriting!C15/12 -> 4090.9588 | F88: =D88-E88 -> 998.60527 | G88: =C88-F88 -> 700308.62 | H88: =H87+F88 -> 64691.379
B89: 82 | C89: =G88 -> 700308.62 | D89: =underwriting!D20 -> 5089.5641 | E89: =C89*underwriting!C15/12 -> 4085.1336 | F89: =D89-E89 -> 1004.4305 | G89: =C89-F89 -> 699304.19 | H89: =H88+F89 -> 65695.81
B90: 83 | C90: =G89 -> 699304.19 | D90: =underwriting!D20 -> 5089.5641 | E90: =C90*underwriting!C15/12 -> 4079.2744 | F90: =D90-E90 -> 1010.2896 | G90: =C90-F90 -> 698293.9 | H90: =H89+F90 -> 66706.099
B91: 84 | C91: =G90 -> 698293.9 | D91: =underwriting!D20 -> 5089.5641 | E91: =C91*underwriting!C15/12 -> 4073.3811 | F91: =D91-E91 -> 1016.183 | G91: =C91-F91 -> 697277.72 | H91: =H90+F91 -> 67722.282
B92: 85 | C92: =G91 -> 697277.72 | D92: =underwriting!D20 -> 5089.5641 | E92: =C92*underwriting!C15/12 -> 4067.4534 | F92: =D92-E92 -> 1022.1107 | G92: =C92-F92 -> 696255.61 | H92: =H91+F92 -> 68744.393
B93: 86 | C93: =G92 -> 696255.61 | D93: =underwriting!D20 -> 5089.5641 | E93: =C93*underwriting!C15/12 -> 4061.491 | F93: =D93-E93 -> 1028.073 | G93: =C93-F93 -> 695227.53 | H93: =H92+F93 -> 69772.466
B94: 87 | C94: =G93 -> 695227.53 | D94: =underwriting!D20 -> 5089.5641 | E94: =C94*underwriting!C15/12 -> 4055.4939 | F94: =D94-E94 -> 1034.0701 | G94: =C94-F94 -> 694193.46 | H94: =H93+F94 -> 70806.536
B95: 88 | C95: =G94 -> 694193.46 | D95: =underwriting!D20 -> 5089.5641 | E95: =C95*underwriting!C15/12 -> 4049.4619 | F95: =D95-E95 -> 1040.1022 | G95: =C95-F95 -> 693153.36 | H95: =H94+F95 -> 71846.638
B96: 89 | C96: =G95 -> 693153.36 | D96: =underwriting!D20 -> 5089.5641 | E96: =C96*underwriting!C15/12 -> 4043.3946 | F96: =D96-E96 -> 1046.1695 | G96: =C96-F96 -> 692107.19 | H96: =H95+F96 -> 72892.808
B97: 90 | C97: =G96 -> 692107.19 | D97: =underwriting!D20 -> 5089.5641 | E97: =C97*underwriting!C15/12 -> 4037.292 | F97: =D97-E97 -> 1052.2721 | G97: =C97-F97 -> 691054.92 | H97: =H96+F97 -> 73945.08
B98: 91 | C98: =G97 -> 691054.92 | D98: =underwriting!D20 -> 5089.5641 | E98: =C98*underwriting!C15/12 -> 4031.1537 | F98: =D98-E98 -> 1058.4104 | G98: =C98-F98 -> 689996.51 | H98: =H97+F98 -> 75003.49
B99: 92 | C99: =G98 -> 689996.51 | D99: =underwriting!D20 -> 5089.5641 | E99: =C99*underwriting!C15/12 -> 4024.9796 | F99: =D99-E99 -> 1064.5844 | G99: =C99-F99 -> 688931.93 | H99: =H98+F99 -> 76068.075
B100: 93 | C100: =G99 -> 688931.93 | D100: =underwriting!D20 -> 5089.5641 | E100: =C100*underwriting!C15/12 -> 4018.7696 | F100: =D100-E100 -> 1070.7945 | G100: =C100-F100 -> 687861.13 | H100: =H99+F100 -> 77138.869
B101: 94 | C101: =G100 -> 687861.13 | D101: =underwriting!D20 -> 5089.5641 | E101: =C101*underwriting!C15/12 -> 4012.5233 | F101: =D101-E101 -> 1077.0408 | G101: =C101-F101 -> 686784.09 | H101: =H100+F101 -> 78215.91
...
